License.txt
README.md
setup.py
Topsis_Nandini_102017101.egg-info/PKG-INFO
Topsis_Nandini_102017101.egg-info/SOURCES.txt
Topsis_Nandini_102017101.egg-info/dependency_links.txt
Topsis_Nandini_102017101.egg-info/entry_points.txt
Topsis_Nandini_102017101.egg-info/requires.txt
Topsis_Nandini_102017101.egg-info/top_level.txt
topsis_package/func.py