Metadata-Version: 2.1
Name: Topsis-Nandini-102017101
Version: 0.0.2
Summary: This is a Python Package implementing TOPSIS used for multi-criteria decision analysis method
Author: Nandini Goel
Author-email: nandinigoel09@gmail.com
License: MIT
Keywords: topsis,mcda,UCS654,TIET
Classifier: Development Status :: 3 - Alpha
Classifier: Intended Audience :: Developers
Classifier: Topic :: Software Development :: Build Tools
Classifier: License :: OSI Approved :: MIT License
License-File: License.txt
